{
  "mode": "pre",
  "tag": "alpha",
  "initialVersions": {
    "@unipasswallet/abi": "0.2.0",
    "@unipasswallet/deployer": "0.2.0",
    "@unipasswallet/dkim": "0.2.0",
    "@unipasswallet/dkim-base": "0.2.0",
    "@unipasswallet/keys": "0.2.0",
    "@unipasswallet/network": "0.2.0",
    "@unipasswallet/provider": "0.2.0",
    "@unipasswallet/relayer": "0.2.0",
    "@unipasswallet/sdk": "0.2.0",
    "@unipasswallet/transaction-builders": "0.2.0",
    "@unipasswallet/transactions": "0.2.0",
    "@unipasswallet/utils": "0.2.0",
    "@unipasswallet/wallet": "0.2.0"
  },
  "changesets": [
    "cool-keys-judge",
    "dirty-hornets-end",
    "fluffy-pears-jam",
    "green-frogs-pretend",
    "hot-impalas-buy",
    "sharp-knives-cross",
    "spicy-cherries-share",
    "spotty-ravens-give",
    "sweet-pillows-kneel",
    "thin-clouds-sniff",
    "twelve-ladybugs-sing"
  ]
}
